rdltr/__init__.py
rdltr/__main__.py
rdltr/config.py
rdltr/articles/__init__.py
rdltr/articles/articles.py
rdltr/articles/articles_utils.py
rdltr/articles/categories.py
rdltr/articles/model.py
rdltr/articles/tags.py
rdltr/dist/favicon.ico
rdltr/dist/index.html
rdltr/dist/static/index-DWOSpNDj.css
rdltr/dist/static/index-DgtYDKye.js
rdltr/migrations/README
rdltr/migrations/__init__.py
rdltr/migrations/alembic.ini
rdltr/migrations/env.py
rdltr/migrations/script.py.mako
rdltr/migrations/versions/01_3a45dbc8708e_user.py
rdltr/migrations/versions/02_9b52e07d1b4b_articles.py
rdltr/migrations/versions/03_73ab306aefac_favorite.py
rdltr/migrations/versions/__init__.py
rdltr/users/__init__.py
rdltr/users/auth.py
rdltr/users/model.py
rdltr/users/utils.py
rdltr-0.1.16.dist-info/LICENSE
rdltr-0.1.16.dist-info/METADATA
rdltr-0.1.16.dist-info/WHEEL
rdltr-0.1.16.dist-info/entry_points.txt
rdltr-0.1.16.dist-info/top_level.txt
rdltr-0.1.16.dist-info/RECORD
