Metadata-Version: 2.1
Name: rdltr
Version: 0.1.16
Summary: simple read-it-later app
Home-page: https://github.com/SamR1/rdltr
Author: SamR1
License: GNU General Public License v3.0
Project-URL: Documentation, https://samr1.github.io/rdltr
Platform: linux
Classifier: Development Status :: 4 - Beta
Classifier: Framework :: Flask
Classifier: Intended Audience :: Developers
Classifier: License :: OSI Approved :: GNU General Public License v3 (GPLv3)
Classifier: Operating System :: POSIX :: Linux
Classifier: Programming Language :: Python :: 3
Classifier: Programming Language :: Python :: 3.8
Classifier: Programming Language :: Python :: 3.9
Classifier: Programming Language :: Python :: 3.10
Classifier: Programming Language :: Python :: 3.11
Classifier: Programming Language :: Python :: 3.12
Classifier: Programming Language :: JavaScript
Classifier: Topic :: Internet :: WWW/HTTP
Requires-Python: >=3.8.1
License-File: LICENSE
Requires-Dist: beautifulsoup4 ==4.12.3
Requires-Dist: Flask ==3.0.3
Requires-Dist: Flask-Bcrypt ==1.0.1
Requires-Dist: Flask-Migrate ==4.0.7
Requires-Dist: Flask-SQLAlchemy ==3.0.5
Requires-Dist: gunicorn ==22.0.0
Requires-Dist: lxml[html_clean] ==5.2.1
Requires-Dist: PyJWT ==2.8.0
Requires-Dist: readability-lxml ==0.8.1
Requires-Dist: requests ==2.31.0
Requires-Dist: sqlalchemy ==1.4.52
Provides-Extra: doc
Requires-Dist: sphinx ; extra == 'doc'
Requires-Dist: sphinx-rtd-theme ; extra == 'doc'
Requires-Dist: recommonmark ; extra == 'doc'
Provides-Extra: test
Requires-Dist: bandit ; extra == 'test'
Requires-Dist: pytest-black ; extra == 'test'
Requires-Dist: pytest-cov ; extra == 'test'
Requires-Dist: pytest-flake8 ; extra == 'test'
Requires-Dist: pytest-html ==3.2.0 ; extra == 'test'
Requires-Dist: pytest-isort ; extra == 'test'
Requires-Dist: pytest-mypy ; extra == 'test'
Requires-Dist: pytest-selenium ; extra == 'test'
Requires-Dist: selenium ==4.9.0 ; extra == 'test'
Requires-Dist: types-requests ; extra == 'test'
